Workbook

Sheet Scorecard
A1: BCM PHYSICAL PD — AUDIO RECORDING SCORECARD (V2.0 Simple)
A2: Evaluator: fill the yellow cells only. For each item choose Yes (fully said with names/numbers), Half (mentioned but vague/incomplete) or No (not said). Score, result and the BCM's "My Result" page fill automatically.
A4: Application ID | C4: Recording length (minutes)
A5: Customer name | C5: Recorded same day as visits? (Yes/No)
A6: BCM name | C6: Farm / dairy / other family income in this case? (Yes/No)
A7: Date of PD & recording | C7: Evaluator
A9: No | B9: WHAT THE BCM MUST SAY IN THE RECORDING | C9: Points | D9: MUST | E9: Covered? (Yes / Half / No) | F9: Score | G9: What was missing — evaluator note | H9: lost (helper)
A10: A. VISIT & PHOTOS | C10: 10 | G10: Minute 0–2
A11: A1 | B11: Start with: Application ID, customer name, village/town, loan amount asked. Say that you checked the CRIF report and BPS score before going. | C11: 2 | F11: =IF(E11="Yes",C11,IF(E11="Half",C11/2,0)) -> 0 | H11: =IF(AND("A"="C",$E$6="No"),0,IF(E11="Yes",0,IF(E11="Half",C11/2,C11))+IF(E11="Yes",0,(1000-ROW())/100000)) -> 2.00989
A12: A2 | B12: Say that you met the BORROWER HIMSELF at his business — not on phone, not through a relative. Date, time, and who came with you. | C12: 2 | D12: MUST | F12: =IF(E12="Yes",C12,IF(E12="Half",C12/2,0)) -> 0 | H12: =IF(AND("A"="C",$E$6="No"),0,IF(E12="Yes",0,IF(E12="Half",C12/2,C12))+IF(E12="Yes",0,(1000-ROW())/100000)) -> 2.00988
A13: A3 | B13: Time spent: business (start–end) and home (start–end). Total must be at least 1 hour (normally 1 to 1.5 hours). | C13: 2 | F13: =IF(E13="Yes",C13,IF(E13="Half",C13/2,0)) -> 0 | H13: =IF(AND("A"="C",$E$6="No"),0,IF(E13="Yes",0,IF(E13="Half",C13/2,C13))+IF(E13="Yes",0,(1000-ROW())/100000)) -> 2.00987
A14: A4 | B14: Home and property visited (say if home and property are the same house). Co-borrower and family met at home. | C14: 2 | F14: =IF(E14="Yes",C14,IF(E14="Half",C14/2,0)) -> 0 | H14: =IF(AND("A"="C",$E$6="No"),0,IF(E14="Yes",0,IF(E14="Half",C14/2,C14))+IF(E14="Yes",0,(1000-ROW())/100000)) -> 2.00986
A15: A5 | B15: Photos taken and uploaded: signboard, QR code, FULL stock, purchase bills, sales bills / register / khata, mandi receipts, every room of the house, household items, electricity meter, both business neighbours, both home neighbours, land / animals (if any), property papers. | C15: 2 | F15: =IF(E15="Yes",C15,IF(E15="Half",C15/2,0)) -> 0 | H15: =IF(AND("A"="C",$E$6="No"),0,IF(E15="Yes",0,IF(E15="Half",C15/2,C15))+IF(E15="Yes",0,(1000-ROW())/100000)) -> 2.00985
A16: B. BUSINESS (say this for EVERY business — borrower's and family members') | C16: 30 | G16: Minute 2–9
A17: B1 | B17: What you SAW: shop/unit size, how much stock, how many staff, customers during your visit, machines, signboard. Every business visited — including one run by wife, son, father. | C17: 3 | D17: MUST | F17: =IF(E17="Yes",C17,IF(E17="Half",C17/2,0)) -> 0 | H17: =IF(AND("B"="C",$E$6="No"),0,IF(E17="Yes",0,IF(E17="Half",C17/2,C17))+IF(E17="Yes",0,(1000-ROW())/100000)) -> 3.00983
A18: B2 | B18: Who actually runs it; running since which year; what the borrower did BEFORE this; new business or family business for generations; shop owned or rented (rent, years here); licence seen (Udyam / Gumasta / GST / FSSAI). | C18: 3 | F18: =IF(E18="Yes",C18,IF(E18="Half",C18/2,0)) -> 0 | H18: =IF(AND("B"="C",$E$6="No"),0,IF(E18="Yes",0,IF(E18="Half",C18/2,C18))+IF(E18="Yes",0,(1000-ROW())/100000)) -> 3.00982
A19: B3 | B19: PURCHASES: buys material from where; purchase bills of last 12 months seen?; % paid by bank/UPI and % by cash; TOP 5 SUPPLIERS with names and mobile numbers; credit taken from suppliers (days, amount due). | C19: 4 | F19: =IF(E19="Yes",C19,IF(E19="Half",C19/2,0)) -> 0 | H19: =IF(AND("B"="C",$E$6="No"),0,IF(E19="Yes",0,IF(E19="Half",C19/2,C19))+IF(E19="Yes",0,(1000-ROW())/100000)) -> 4.00981
A20: B4 | B20: SALES: who buys; % received in cash and % by UPI; QR code / UPI is in WHOSE name; sales today and average daily sales; average monthly sales; lean months and daily sales in lean months; udhaar (credit) given to customers — how much. | C20: 4 | F20: =IF(E20="Yes",C20,IF(E20="Half",C20/2,0)) -> 0 | H20: =IF(AND("B"="C",$E$6="No"),0,IF(E20="Yes",0,IF(E20="Half",C20/2,C20))+IF(E20="Yes",0,(1000-ROW())/100000)) -> 4.0098
A21: B5 | B21: STOCK: you counted the stock yourself — your value (Rs.) vs what the customer says. | C21: 2 | F21: =IF(E21="Yes",C21,IF(E21="Half",C21/2,0)) -> 0 | H21: =IF(AND("B"="C",$E$6="No"),0,IF(E21="Yes",0,IF(E21="Half",C21/2,C21))+IF(E21="Yes",0,(1000-ROW())/100000)) -> 2.00979
A22: B6 | B22: INCOME MATHS said aloud: monthly sales × margin % − expenses (rent, electricity, salary, transport) = monthly income. CHECK with AA: UPI credits per month ÷ UPI % = real sales. Say which document supports each number. If a number has no support, take the lower figure — do not accept the customer's number just because he said it. | C22: 4 | F22: =IF(E22="Yes",C22,IF(E22="Half",C22/2,0)) -> 0 | H22: =IF(AND("B"="C",$E$6="No"),0,IF(E22="Yes",0,IF(E22="Half",C22/2,C22))+IF(E22="Yes",0,(1000-ROW())/100000)) -> 4.00978
A23: B7 | B23: AA (Account Aggregator) triggered on PRAGATI for ALL bank accounts of borrower and co-borrowers — name each account and say SUCCESS or FAILED for each. Documents seen: bills, register, khata, passbook, kata parchi. | C23: 3 | D23: MUST | F23: =IF(E23="Yes",C23,IF(E23="Half",C23/2,0)) -> 0 | H23: =IF(AND("B"="C",$E$6="No"),0,IF(E23="Yes",0,IF(E23="Half",C23/2,C23))+IF(E23="Yes",0,(1000-ROW())/100000)) -> 3.00977
A24: B8 | B24: 2 BUSINESS NEIGHBOURS: name, shop, mobile number, how long this business is running here, what they said about the customer. Photos taken. | C24: 4 | D24: MUST | F24: =IF(E24="Yes",C24,IF(E24="Half",C24/2,0)) -> 0 | H24: =IF(AND("B"="C",$E$6="No"),0,IF(E24="Yes",0,IF(E24="Half",C24/2,C24))+IF(E24="Yes",0,(1000-ROW())/100000)) -> 4.00976
A25: B9 | B25: YOUR VIEW on each business: genuine and running — or doubt (borrowed stock, arranged setup, too small for the claim). Say it clearly. | C25: 3 | F25: =IF(E25="Yes",C25,IF(E25="Half",C25/2,0)) -> 0 | H25: =IF(AND("B"="C",$E$6="No"),0,IF(E25="Yes",0,IF(E25="Half",C25/2,C25))+IF(E25="Yes",0,(1000-ROW())/100000)) -> 3.00975
A26: C. FARM, DAIRY & OTHER FAMILY INCOME (if none, say so — then this group is not counted) | C26: 10 | G26: Minute 9–11
A27: C1 | B27: LAND: acres, Khasra number, in whose name, borrower's share; checked on Bhulekh / SVAMITVA; land seen (or GPS video if far). | C27: 3 | F27: =IF($E$6="No",0,IF(E27="Yes",C27,IF(E27="Half",C27/2,0))) -> 0 | H27: =IF(AND("C"="C",$E$6="No"),0,IF(E27="Yes",0,IF(E27="Half",C27/2,C27))+IF(E27="Yes",0,(1000-ROW())/100000)) -> 3.00973
A28: C2 | B28: CROPS: which crops each season, yield and price, mandi receipts / PM-KISAN credit seen; KCC or JLG loan — bank, limit, regular or overdue (if overdue: reason and which land). | C28: 3 | F28: =IF($E$6="No",0,IF(E28="Yes",C28,IF(E28="Half",C28/2,0))) -> 0 | H28: =IF(AND("C"="C",$E$6="No"),0,IF(E28="Yes",0,IF(E28="Half",C28/2,C28))+IF(E28="Yes",0,(1000-ROW())/100000)) -> 3.00972
A29: C3 | B29: DAIRY: cows/buffaloes counted by you (photo), litres per day, milk sold to whom (Sanchi / society / private), rate, proof (passbook / slips / UPI). | C29: 2 | F29: =IF($E$6="No",0,IF(E29="Yes",C29,IF(E29="Half",C29/2,0))) -> 0 | H29: =IF(AND("C"="C",$E$6="No"),0,IF(E29="Yes",0,IF(E29="Half",C29/2,C29))+IF(E29="Yes",0,(1000-ROW())/100000)) -> 2.00971
A30: C4 | B30: OTHER INCOME: what each family member does and earns (salary, pension, rent, labour, driving, tailoring), with proof. Say which incomes you are COUNTING and which NOT — and why. | C30: 2 | F30: =IF($E$6="No",0,IF(E30="Yes",C30,IF(E30="Half",C30/2,0))) -> 0 | H30: =IF(AND("C"="C",$E$6="No"),0,IF(E30="Yes",0,IF(E30="Half",C30/2,C30))+IF(E30="Yes",0,(1000-ROW())/100000)) -> 2.0097
A31: D. LOANS & REPAYMENT | C31: 12 | G31: Minute 11–14
A32: D1 | B32: EVERY loan in the CRIF of borrower, co-borrowers AND guarantors — lender, EMI, outstanding — discussed with them. Plus loans not in CRIF: MFI / SHG / JLG, KCC / society, gold, hand loans, chit / committee, supplier credit. Anything found on the ground that was not disclosed — say it. | C32: 4 | D32: MUST | F32: =IF(E32="Yes",C32,IF(E32="Half",C32/2,0)) -> 0 | H32: =IF(AND("D"="C",$E$6="No"),0,IF(E32="Yes",0,IF(E32="Half",C32/2,C32))+IF(E32="Yes",0,(1000-ROW())/100000)) -> 4.00968
A33: D2 | B33: DEFAULTS: for every overdue / DPD / settled account — the reason in the customer's words and your view (justified or not). EMIs paid by bank (NACH) or in cash to an agent? Is he a regular defaulter who does not care, or one-time with a clear reason? | C33: 3 | F33: =IF(E33="Yes",C33,IF(E33="Half",C33/2,0)) -> 0 | H33: =IF(AND("D"="C",$E$6="No"),0,IF(E33="Yes",0,IF(E33="Half",C33/2,C33))+IF(E33="Yes",0,(1000-ROW())/100000)) -> 3.00967
A34: D3 | B34: Family expenses per month, school fees, any big expense coming in 12 months (marriage, house construction, vehicle). | C34: 2 | F34: =IF(E34="Yes",C34,IF(E34="Half",C34/2,0)) -> 0 | H34: =IF(AND("D"="C",$E$6="No"),0,IF(E34="Yes",0,IF(E34="Half",C34/2,C34))+IF(E34="Yes",0,(1000-ROW())/100000)) -> 2.00966
A35: D4 | B35: Loans applied in the last 3 months: where, how much, result, WHY not sanctioned yet, TOTAL money he wants from all lenders together. Then: income − expenses − EMIs = surplus, compared with the proposed EMI. | C35: 3 | F35: =IF(E35="Yes",C35,IF(E35="Half",C35/2,0)) -> 0 | H35: =IF(AND("D"="C",$E$6="No"),0,IF(E35="Yes",0,IF(E35="Half",C35/2,C35))+IF(E35="Yes",0,(1000-ROW())/100000)) -> 3.00965
A36: E. FAMILY & HOME | C36: 12 | G36: Minute 14–17
A37: E1 | B37: HOME: own or rented, years living here, pucca / kachha, rooms; electricity bill in whose name; items seen — tractor, car, bike, TV, fridge, washing machine, smartphones (how many), cooler / AC, gas, electricity meter. Does the standard of living match the income claimed? | C37: 3 | F37: =IF(E37="Yes",C37,IF(E37="Half",C37/2,0)) -> 0 | H37: =IF(AND("E"="C",$E$6="No"),0,IF(E37="Yes",0,IF(E37="Half",C37/2,C37))+IF(E37="Yes",0,(1000-ROW())/100000)) -> 3.00963
A38: E2 | B38: CO-BORROWER (wife / mother) met in person — knows the loan amount, the EMI and that the HOUSE WILL BE MORTGAGED. Each family member: what they do, aware of the loan, supportive? KYC originals (Aadhaar / PAN / Voter) and Samagra ID of borrower and ALL co-borrowers checked and matched. | C38: 4 | D38: MUST | F38: =IF(E38="Yes",C38,IF(E38="Half",C38/2,0)) -> 0 | H38: =IF(AND("E"="C",$E$6="No"),0,IF(E38="Yes",0,IF(E38="Half",C38/2,C38))+IF(E38="Yes",0,(1000-ROW())/100000)) -> 4.00962
A39: E3 | B39: 2 HOME NEIGHBOURS: name, mobile number, how long the family is staying here, conduct, any dispute. Photos taken. | C39: 3 | D39: MUST | F39: =IF(E39="Yes",C39,IF(E39="Half",C39/2,0)) -> 0 | H39: =IF(AND("E"="C",$E$6="No"),0,IF(E39="Yes",0,IF(E39="Half",C39/2,C39))+IF(E39="Yes",0,(1000-ROW())/100000)) -> 3.00961
A40: E4 | B40: Told the customer and family: this is a Loan Against Property (house mortgaged), the EMI amount, Clean Track Reward (last 3 EMIs waived on clean repayment), ZERO COMMISSION — pay nobody, Prodigee works on trust and integrity. | C40: 2 | F40: =IF(E40="Yes",C40,IF(E40="Half",C40/2,0)) -> 0 | H40: =IF(AND("E"="C",$E$6="No"),0,IF(E40="Yes",0,IF(E40="Half",C40/2,C40))+IF(E40="Yes",0,(1000-ROW())/100000)) -> 2.0096
A41: F. PROPERTY | C41: 14 | G41: Minute 17–20
A42: F1 | B42: Property: house / shop / plot, self-occupied or rented out, pucca, age, area (sq.ft), road access, kitchen and toilet, condition. | C42: 3 | F42: =IF(E42="Yes",C42,IF(E42="Half",C42/2,0)) -> 0 | H42: =IF(AND("F"="C",$E$6="No"),0,IF(E42="Yes",0,IF(E42="Half",C42/2,C42))+IF(E42="Yes",0,(1000-ROW())/100000)) -> 3.00958
A43: F2 | B43: ORIGINAL papers seen with your own eyes (Sale Deed / Patta / 5-pager — say which); in whose name; how he got it; mutation done? ALL owners and legal heirs are CO-BORROWERS on this loan — name them. | C43: 4 | D43: MUST | F43: =IF(E43="Yes",C43,IF(E43="Half",C43/2,0)) -> 0 | H43: =IF(AND("F"="C",$E$6="No"),0,IF(E43="Yes",0,IF(E43="Half",C43/2,C43))+IF(E43="Yes",0,(1000-ROW())/100000)) -> 4.00957
A44: F3 | B44: Papers genuine? (registry seal and number, pages complete, Panchayat seal / signature). Already mortgaged with any other bank / finance company? Original papers lying with any other lender? Asked the family; checked CRIF for secured loans. For panchayat property: Patta / SVAMITVA record checked. | C44: 3 | F44: =IF(E44="Yes",C44,IF(E44="Half",C44/2,0)) -> 0 | H44: =IF(AND("F"="C",$E$6="No"),0,IF(E44="Yes",0,IF(E44="Half",C44/2,C44))+IF(E44="Yes",0,(1000-ROW())/100000)) -> 3.00956
A45: F4 | B45: Approximate value with the basis (local rate per sq.ft, a recent sale nearby, neighbour's view); distress value; loan amount vs value. | C45: 2 | F45: =IF(E45="Yes",C45,IF(E45="Half",C45/2,0)) -> 0 | H45: =IF(AND("F"="C",$E$6="No"),0,IF(E45="Yes",0,IF(E45="Half",C45/2,C45))+IF(E45="Yes",0,(1000-ROW())/100000)) -> 2.00955
A46: F5 | B46: Risks: any dispute, ST / tribal land, high-tension line / river bank / encroachment, negative area, demolition risk — say "none" if none. | C46: 2 | F46: =IF(E46="Yes",C46,IF(E46="Half",C46/2,0)) -> 0 | H46: =IF(AND("F"="C",$E$6="No"),0,IF(E46="Yes",0,IF(E46="Half",C46/2,C46))+IF(E46="Yes",0,(1000-ROW())/100000)) -> 2.00954
A47: G. LOAN PURPOSE & YOUR VIEW | C47: 12 | G47: Minute 20–22
A48: G1 | B48: Loan purpose: how much for what, where, when; is the need visible on the ground (empty shelves, loans to be closed); not a restricted use. | C48: 3 | F48: =IF(E48="Yes",C48,IF(E48="Half",C48/2,0)) -> 0 | H48: =IF(AND("G"="C",$E$6="No"),0,IF(E48="Yes",0,IF(E48="Half",C48/2,C48))+IF(E48="Yes",0,(1000-ROW())/100000)) -> 3.00952
A49: G2 | B49: INTENT & INTEGRITY — answer each one clearly: (1) business genuine? (2) sales and purchase numbers true or inflated? (3) defaults justified? (4) regular defaulter? (5) family aware and supportive? (6) all property owners on the loan? (7) papers genuine? (8) customer open or evasive about accounts, bills, loans? (9) any middleman or commission? | C49: 4 | D49: MUST | F49: =IF(E49="Yes",C49,IF(E49="Half",C49/2,0)) -> 0 | H49: =IF(AND("G"="C",$E$6="No"),0,IF(E49="Yes",0,IF(E49="Half",C49/2,C49))+IF(E49="Yes",0,(1000-ROW())/100000)) -> 4.00951
A50: G3 | B50: WARNING SIGNS seen — say each one, or say "none": staged / fake business · hidden loans · family unaware · doubtful papers or property mortgaged elsewhere · commission or middleman · numbers not matching AA / bills. | C50: 3 | F50: =IF(E50="Yes",C50,IF(E50="Half",C50/2,0)) -> 0 | H50: =IF(AND("G"="C",$E$6="No"),0,IF(E50="Yes",0,IF(E50="Half",C50/2,C50))+IF(E50="Yes",0,(1000-ROW())/100000)) -> 3.0095
A51: G4 | B51: What you could NOT verify — say it honestly. Your overall view: total family income vs loan asked, ability and intention to repay. (This is your view — the decision is taken later on PRAGATI.) | C51: 2 | F51: =IF(E51="Yes",C51,IF(E51="Half",C51/2,0)) -> 0 | H51: =IF(AND("G"="C",$E$6="No"),0,IF(E51="Yes",0,IF(E51="Half",C51/2,C51))+IF(E51="Yes",0,(1000-ROW())/100000)) -> 2.00949
A53: Recording valid? (15–25 minutes AND same day) | C53: =IF(OR(E4="",E5=""),"Fill length & same-day",IF(AND(E4>=15,E4<=25,E5="Yes"),"YES","NO — not accepted")) -> Fill length & same-day
A54: Points applicable (Group C removed if no farm/dairy/other income) | C54: =100-IF(E6="No",10,0) -> 100
A55: Points scored | C55: =SUM(F11:F51) -> 0
A56: SCORE (out of 100) | C56: =ROUND(C55/C54*100,0) -> 0
A57: MUST items not fully covered (count) | C57: =IF(E12<>"Yes",1,0)+IF(E17<>"Yes",1,0)+IF(E23<>"Yes",1,0)+IF(E24<>"Yes",1,0)+IF(E32<>"Yes",1,0)+IF(E38<>"Yes",1,0)+IF(E39<>"Yes",1,0)+IF(E43<>"Yes",1,0)+IF(E49<>"Yes",1,0) -> 9
A58: MUST items missed (list) | C58: =IF(C57=0,"None",_xlfn.TEXTJOIN(", ",TRUE(),IF(E12<>"Yes",A12,""),IF(E17<>"Yes",A17,""),IF(E23<>"Yes",A23,""),IF(E24<>"Yes",A24,""),IF(E32<>"Yes",A32,""),IF(E38<>"Yes",A38,""),IF(E39<>"Yes",A39,""),IF(E43<>"Yes",A43,""),IF(E49<>"Yes",A49,""))) -> A2, B1, B7, B8, D1, E2, E3, F2, G2
A59: RESULT | C59: =IF(C53<>"YES","NOT ACCEPTED — recording under 15 min / over 25 min / not same day. Record again.",IF(C57>0,"NOT ACCEPTED — MUST item(s) missed: "&C58&". Record the missed points again.",IF(C56>=90,"EXCELLENT — accepted. Score "&C56&"/100.",IF(C56>=75,"ACCEPTED — Score "&C56&"/100. See My Result for what to do better.","NOT ACCEPTED — Score "&C56&"/100 is below 75. Record the missed points again.")))) -> NOT ACCEPTED — recording under 15 min / over 25 min / not same day. Record again.

Sheet My Result
A1: MY PD AUDIO RESULT
A2: Read this after every recording. It shows your score, what you missed and what to cover first next time. Nothing to fill here — it comes from the Scorecard.
A4: BCM | C4: =Scorecard!B6 -> 0
A5: Customer | C5: =Scorecard!B5 -> 0
A6: Application ID | C6: =Scorecard!B4 -> 0
A7: Date | C7: =Scorecard!B7 -> 0
A8: Recording length (min) | C8: =Scorecard!E4 -> 0
A10: MY SCORE | C10: =Scorecard!C56&" / 100" -> 0 / 100
A11: RESULT | C11: =Scorecard!C59 -> NOT ACCEPTED — recording under 15 min / over 25 min / not same day. Record again.
A12: Minimum to pass: 75. All MUST items must be Yes. 90+ is Excellent.
B14: HOW I DID — GROUP-WISE | C14: Points | D14: I got | E14: % | F14: Comment
A15: A | B15: Visit & Photos | C15: 10 | D15: =IF(C15="N/A","N/A",SUM(Scorecard!F11:F15)) -> 0 | E15: =IF(C15="N/A","N/A",ROUND(D15/C15*100,0)&"%") -> 0% | F15: =IF(C15="N/A","Not applicable in this case",IF(D15=C15,"Fully covered",IF(D15>=C15*0.75,"Good — small gaps",IF(D15>=C15*0.5,"Weak — see items below","Mostly missed — see items below")))) -> Mostly missed — see items below
A16: B | B16: Business | C16: 30 | D16: =IF(C16="N/A","N/A",SUM(Scorecard!F17:F25)) -> 0 | E16: =IF(C16="N/A","N/A",ROUND(D16/C16*100,0)&"%") -> 0% | F16: =IF(C16="N/A","Not applicable in this case",IF(D16=C16,"Fully covered",IF(D16>=C16*0.75,"Good — small gaps",IF(D16>=C16*0.5,"Weak — see items below","Mostly missed — see items below")))) -> Mostly missed — see items below
A17: C | B17: Farm, Dairy & Other Family Income | C17: =IF(Scorecard!$E$6="No","N/A",10) -> 10 | D17: =IF(C17="N/A","N/A",SUM(Scorecard!F27:F30)) -> 0 | E17: =IF(C17="N/A","N/A",ROUND(D17/C17*100,0)&"%") -> 0% | F17: =IF(C17="N/A","Not applicable in this case",IF(D17=C17,"Fully covered",IF(D17>=C17*0.75,"Good — small gaps",IF(D17>=C17*0.5,"Weak — see items below","Mostly missed — see items below")))) -> Mostly missed — see items below
A18: D | B18: Loans & Repayment | C18: 12 | D18: =IF(C18="N/A","N/A",SUM(Scorecard!F32:F35)) -> 0 | E18: =IF(C18="N/A","N/A",ROUND(D18/C18*100,0)&"%") -> 0% | F18: =IF(C18="N/A","Not applicable in this case",IF(D18=C18,"Fully covered",IF(D18>=C18*0.75,"Good — small gaps",IF(D18>=C18*0.5,"Weak — see items below","Mostly missed — see items below")))) -> Mostly missed — see items below
A19: E | B19: Family & Home | C19: 12 | D19: =IF(C19="N/A","N/A",SUM(Scorecard!F37:F40)) -> 0 | E19: =IF(C19="N/A","N/A",ROUND(D19/C19*100,0)&"%") -> 0% | F19: =IF(C19="N/A","Not applicable in this case",IF(D19=C19,"Fully covered",IF(D19>=C19*0.75,"Good — small gaps",IF(D19>=C19*0.5,"Weak — see items below","Mostly missed — see items below")))) -> Mostly missed — see items below
A20: F | B20: Property | C20: 14 | D20: =IF(C20="N/A","N/A",SUM(Scorecard!F42:F46)) -> 0 | E20: =IF(C20="N/A","N/A",ROUND(D20/C20*100,0)&"%") -> 0% | F20: =IF(C20="N/A","Not applicable in this case",IF(D20=C20,"Fully covered",IF(D20>=C20*0.75,"Good — small gaps",IF(D20>=C20*0.5,"Weak — see items below","Mostly missed — see items below")))) -> Mostly missed — see items below
A21: G | B21: Loan Purpose & Your View | C21: 12 | D21: =IF(C21="N/A","N/A",SUM(Scorecard!F48:F51)) -> 0 | E21: =IF(C21="N/A","N/A",ROUND(D21/C21*100,0)&"%") -> 0% | F21: =IF(C21="N/A","Not applicable in this case",IF(D21=C21,"Fully covered",IF(D21>=C21*0.75,"Good — small gaps",IF(D21>=C21*0.5,"Weak — see items below","Mostly missed — see items below")))) -> Mostly missed — see items below
A23: NEXT TIME — COVER THESE FIRST (the 3 items where I lost most points)
A24: 1 | B24: =IF(LARGE(Scorecard!$H$11:$H$51,1)<0.5,"—",INDEX(Scorecard!$A$11:$A$51,MATCH(LARGE(Scorecard!$H$11:$H$51,1),Scorecard!$H$11:$H$51,0))&" — "&INDEX(Scorecard!$B$11:$B$51,MATCH(LARGE(Scorecard!$H$11:$H$51,1),Scorecard!$H$11:$H$51,0))) -> B3 — PURCHASES: buys material from where; purchase bills of last 12 months seen?; % paid by bank/UPI and % by cash; TOP 5 SUPPLIERS with names and mobile numbers; credit taken from suppliers (days, amount due). | F24: =IF(LARGE(Scorecard!$H$11:$H$51,1)<0.5,"", "Points lost: "&ROUND(LARGE(Scorecard!$H$11:$H$51,1),1)) -> Points lost: 4
A25: 2 | B25: =IF(LARGE(Scorecard!$H$11:$H$51,2)<0.5,"—",INDEX(Scorecard!$A$11:$A$51,MATCH(LARGE(Scorecard!$H$11:$H$51,2),Scorecard!$H$11:$H$51,0))&" — "&INDEX(Scorecard!$B$11:$B$51,MATCH(LARGE(Scorecard!$H$11:$H$51,2),Scorecard!$H$11:$H$51,0))) -> B4 — SALES: who buys; % received in cash and % by UPI; QR code / UPI is in WHOSE name; sales today and average daily sales; average monthly sales; lean months and daily sales in lean months; udhaar (credit) given to customers — how much. | F25: =IF(LARGE(Scorecard!$H$11:$H$51,2)<0.5,"", "Points lost: "&ROUND(LARGE(Scorecard!$H$11:$H$51,2),1)) -> Points lost: 4
A26: 3 | B26: =IF(LARGE(Scorecard!$H$11:$H$51,3)<0.5,"—",INDEX(Scorecard!$A$11:$A$51,MATCH(LARGE(Scorecard!$H$11:$H$51,3),Scorecard!$H$11:$H$51,0))&" — "&INDEX(Scorecard!$B$11:$B$51,MATCH(LARGE(Scorecard!$H$11:$H$51,3),Scorecard!$H$11:$H$51,0))) -> B6 — INCOME MATHS said aloud: monthly sales × margin % − expenses (rent, electricity, salary, transport) = monthly income. CHECK with AA: UPI credits per month ÷ UPI % = real sales. Say which document supports each number. If a number has no support, take the lower figure — do not accept the customer's number just because he said it. | F26: =IF(LARGE(Scorecard!$H$11:$H$51,3)<0.5,"", "Points lost: "&ROUND(LARGE(Scorecard!$H$11:$H$51,3),1)) -> Points lost: 4
A28: No | B28: MY CHECKLIST — WHAT I SAID AND WHAT I MISSED | C28: Points | D28: I got | E28: Mark | F28: What was missing
A29: A. VISIT & PHOTOS
A30: A1 | B30: =Scorecard!B11 -> Start with: Application ID, customer name, village/town, loan amount asked. Say that you checked the CRIF report and BPS score before going. | C30: =Scorecard!C11 -> 2 | D30: =Scorecard!F11 -> 0 | E30: =IF(Scorecard!E11="Yes","✔ Said",IF(Scorecard!E11="Half","½ Half",IF(Scorecard!E11="No","✘ MISSED","?"))) -> ? | F30: =IF(Scorecard!G11="","",Scorecard!G11)
A31: A2 ★ | B31: =Scorecard!B12 -> Say that you met the BORROWER HIMSELF at his business — not on phone, not through a relative. Date, time, and who came with you. | C31: =Scorecard!C12 -> 2 | D31: =Scorecard!F12 -> 0 | E31: =IF(Scorecard!E12="Yes","✔ Said",IF(Scorecard!E12="Half","½ Half",IF(Scorecard!E12="No","✘ MISSED","?"))) -> ? | F31: =IF(Scorecard!G12="","",Scorecard!G12)
A32: A3 | B32: =Scorecard!B13 -> Time spent: business (start–end) and home (start–end). Total must be at least 1 hour (normally 1 to 1.5 hours). | C32: =Scorecard!C13 -> 2 | D32: =Scorecard!F13 -> 0 | E32: =IF(Scorecard!E13="Yes","✔ Said",IF(Scorecard!E13="Half","½ Half",IF(Scorecard!E13="No","✘ MISSED","?"))) -> ? | F32: =IF(Scorecard!G13="","",Scorecard!G13)
A33: A4 | B33: =Scorecard!B14 -> Home and property visited (say if home and property are the same house). Co-borrower and family met at home. | C33: =Scorecard!C14 -> 2 | D33: =Scorecard!F14 -> 0 | E33: =IF(Scorecard!E14="Yes","✔ Said",IF(Scorecard!E14="Half","½ Half",IF(Scorecard!E14="No","✘ MISSED","?"))) -> ? | F33: =IF(Scorecard!G14="","",Scorecard!G14)
A34: A5 | B34: =Scorecard!B15 -> Photos taken and uploaded: signboard, QR code, FULL stock, purchase bills, sales bills / register / khata, mandi receipts, every room of the house, household items, electricity meter, both business neighbours, both home neighbours, land / animals (if any), property papers. | C34: =Scorecard!C15 -> 2 | D34: =Scorecard!F15 -> 0 | E34: =IF(Scorecard!E15="Yes","✔ Said",IF(Scorecard!E15="Half","½ Half",IF(Scorecard!E15="No","✘ MISSED","?"))) -> ? | F34: =IF(Scorecard!G15="","",Scorecard!G15)
A35: B. BUSINESS
A36: B1 ★ | B36: =Scorecard!B17 -> What you SAW: shop/unit size, how much stock, how many staff, customers during your visit, machines, signboard. Every business visited — including one run by wife, son, father. | C36: =Scorecard!C17 -> 3 | D36: =Scorecard!F17 -> 0 | E36: =IF(Scorecard!E17="Yes","✔ Said",IF(Scorecard!E17="Half","½ Half",IF(Scorecard!E17="No","✘ MISSED","?"))) -> ? | F36: =IF(Scorecard!G17="","",Scorecard!G17)
A37: B2 | B37: =Scorecard!B18 -> Who actually runs it; running since which year; what the borrower did BEFORE this; new business or family business for generations; shop owned or rented (rent, years here); licence seen (Udyam / Gumasta / GST / FSSAI). | C37: =Scorecard!C18 -> 3 | D37: =Scorecard!F18 -> 0 | E37: =IF(Scorecard!E18="Yes","✔ Said",IF(Scorecard!E18="Half","½ Half",IF(Scorecard!E18="No","✘ MISSED","?"))) -> ? | F37: =IF(Scorecard!G18="","",Scorecard!G18)
A38: B3 | B38: =Scorecard!B19 -> PURCHASES: buys material from where; purchase bills of last 12 months seen?; % paid by bank/UPI and % by cash; TOP 5 SUPPLIERS with names and mobile numbers; credit taken from suppliers (days, amount due). | C38: =Scorecard!C19 -> 4 | D38: =Scorecard!F19 -> 0 | E38: =IF(Scorecard!E19="Yes","✔ Said",IF(Scorecard!E19="Half","½ Half",IF(Scorecard!E19="No","✘ MISSED","?"))) -> ? | F38: =IF(Scorecard!G19="","",Scorecard!G19)
A39: B4 | B39: =Scorecard!B20 -> SALES: who buys; % received in cash and % by UPI; QR code / UPI is in WHOSE name; sales today and average daily sales; average monthly sales; lean months and daily sales in lean months; udhaar (credit) given to customers — how much. | C39: =Scorecard!C20 -> 4 | D39: =Scorecard!F20 -> 0 | E39: =IF(Scorecard!E20="Yes","✔ Said",IF(Scorecard!E20="Half","½ Half",IF(Scorecard!E20="No","✘ MISSED","?"))) -> ? | F39: =IF(Scorecard!G20="","",Scorecard!G20)
A40: B5 | B40: =Scorecard!B21 -> STOCK: you counted the stock yourself — your value (Rs.) vs what the customer says. | C40: =Scorecard!C21 -> 2 | D40: =Scorecard!F21 -> 0 | E40: =IF(Scorecard!E21="Yes","✔ Said",IF(Scorecard!E21="Half","½ Half",IF(Scorecard!E21="No","✘ MISSED","?"))) -> ? | F40: =IF(Scorecard!G21="","",Scorecard!G21)
A41: B6 | B41: =Scorecard!B22 -> INCOME MATHS said aloud: monthly sales × margin % − expenses (rent, electricity, salary, transport) = monthly income. CHECK with AA: UPI credits per month ÷ UPI % = real sales. Say which document supports each number. If a number has no support, take the lower figure — do not accept the customer's number just because he said it. | C41: =Scorecard!C22 -> 4 | D41: =Scorecard!F22 -> 0 | E41: =IF(Scorecard!E22="Yes","✔ Said",IF(Scorecard!E22="Half","½ Half",IF(Scorecard!E22="No","✘ MISSED","?"))) -> ? | F41: =IF(Scorecard!G22="","",Scorecard!G22)
A42: B7 ★ | B42: =Scorecard!B23 -> AA (Account Aggregator) triggered on PRAGATI for ALL bank accounts of borrower and co-borrowers — name each account and say SUCCESS or FAILED for each. Documents seen: bills, register, khata, passbook, kata parchi. | C42: =Scorecard!C23 -> 3 | D42: =Scorecard!F23 -> 0 | E42: =IF(Scorecard!E23="Yes","✔ Said",IF(Scorecard!E23="Half","½ Half",IF(Scorecard!E23="No","✘ MISSED","?"))) -> ? | F42: =IF(Scorecard!G23="","",Scorecard!G23)
A43: B8 ★ | B43: =Scorecard!B24 -> 2 BUSINESS NEIGHBOURS: name, shop, mobile number, how long this business is running here, what they said about the customer. Photos taken. | C43: =Scorecard!C24 -> 4 | D43: =Scorecard!F24 -> 0 | E43: =IF(Scorecard!E24="Yes","✔ Said",IF(Scorecard!E24="Half","½ Half",IF(Scorecard!E24="No","✘ MISSED","?"))) -> ? | F43: =IF(Scorecard!G24="","",Scorecard!G24)
A44: B9 | B44: =Scorecard!B25 -> YOUR VIEW on each business: genuine and running — or doubt (borrowed stock, arranged setup, too small for the claim). Say it clearly. | C44: =Scorecard!C25 -> 3 | D44: =Scorecard!F25 -> 0 | E44: =IF(Scorecard!E25="Yes","✔ Said",IF(Scorecard!E25="Half","½ Half",IF(Scorecard!E25="No","✘ MISSED","?"))) -> ? | F44: =IF(Scorecard!G25="","",Scorecard!G25)
A45: C. FARM, DAIRY & OTHER FAMILY INCOME
A46: C1 | B46: =Scorecard!B27 -> LAND: acres, Khasra number, in whose name, borrower's share; checked on Bhulekh / SVAMITVA; land seen (or GPS video if far). | C46: =Scorecard!C27 -> 3 | D46: =Scorecard!F27 -> 0 | E46: =IF(Scorecard!$E$6="No","N/A",IF(Scorecard!E27="Yes","✔ Said",IF(Scorecard!E27="Half","½ Half",IF(Scorecard!E27="No","✘ MISSED","?")))) -> ? | F46: =IF(Scorecard!G27="","",Scorecard!G27)
A47: C2 | B47: =Scorecard!B28 -> CROPS: which crops each season, yield and price, mandi receipts / PM-KISAN credit seen; KCC or JLG loan — bank, limit, regular or overdue (if overdue: reason and which land). | C47: =Scorecard!C28 -> 3 | D47: =Scorecard!F28 -> 0 | E47: =IF(Scorecard!$E$6="No","N/A",IF(Scorecard!E28="Yes","✔ Said",IF(Scorecard!E28="Half","½ Half",IF(Scorecard!E28="No","✘ MISSED","?")))) -> ? | F47: =IF(Scorecard!G28="","",Scorecard!G28)
A48: C3 | B48: =Scorecard!B29 -> DAIRY: cows/buffaloes counted by you (photo), litres per day, milk sold to whom (Sanchi / society / private), rate, proof (passbook / slips / UPI). | C48: =Scorecard!C29 -> 2 | D48: =Scorecard!F29 -> 0 | E48: =IF(Scorecard!$E$6="No","N/A",IF(Scorecard!E29="Yes","✔ Said",IF(Scorecard!E29="Half","½ Half",IF(Scorecard!E29="No","✘ MISSED","?")))) -> ? | F48: =IF(Scorecard!G29="","",Scorecard!G29)
A49: C4 | B49: =Scorecard!B30 -> OTHER INCOME: what each family member does and earns (salary, pension, rent, labour, driving, tailoring), with proof. Say which incomes you are COUNTING and which NOT — and why. | C49: =Scorecard!C30 -> 2 | D49: =Scorecard!F30 -> 0 | E49: =IF(Scorecard!$E$6="No","N/A",IF(Scorecard!E30="Yes","✔ Said",IF(Scorecard!E30="Half","½ Half",IF(Scorecard!E30="No","✘ MISSED","?")))) -> ? | F49: =IF(Scorecard!G30="","",Scorecard!G30)
A50: D. LOANS & REPAYMENT
A51: D1 ★ | B51: =Scorecard!B32 -> EVERY loan in the CRIF of borrower, co-borrowers AND guarantors — lender, EMI, outstanding — discussed with them. Plus loans not in CRIF: MFI / SHG / JLG, KCC / society, gold, hand loans, chit / committee, supplier credit. Anything found on the ground that was not disclosed — say it. | C51: =Scorecard!C32 -> 4 | D51: =Scorecard!F32 -> 0 | E51: =IF(Scorecard!E32="Yes","✔ Said",IF(Scorecard!E32="Half","½ Half",IF(Scorecard!E32="No","✘ MISSED","?"))) -> ? | F51: =IF(Scorecard!G32="","",Scorecard!G32)
A52: D2 | B52: =Scorecard!B33 -> DEFAULTS: for every overdue / DPD / settled account — the reason in the customer's words and your view (justified or not). EMIs paid by bank (NACH) or in cash to an agent? Is he a regular defaulter who does not care, or one-time with a clear reason? | C52: =Scorecard!C33 -> 3 | D52: =Scorecard!F33 -> 0 | E52: =IF(Scorecard!E33="Yes","✔ Said",IF(Scorecard!E33="Half","½ Half",IF(Scorecard!E33="No","✘ MISSED","?"))) -> ? | F52: =IF(Scorecard!G33="","",Scorecard!G33)
A53: D3 | B53: =Scorecard!B34 -> Family expenses per month, school fees, any big expense coming in 12 months (marriage, house construction, vehicle). | C53: =Scorecard!C34 -> 2 | D53: =Scorecard!F34 -> 0 | E53: =IF(Scorecard!E34="Yes","✔ Said",IF(Scorecard!E34="Half","½ Half",IF(Scorecard!E34="No","✘ MISSED","?"))) -> ? | F53: =IF(Scorecard!G34="","",Scorecard!G34)
A54: D4 | B54: =Scorecard!B35 -> Loans applied in the last 3 months: where, how much, result, WHY not sanctioned yet, TOTAL money he wants from all lenders together. Then: income − expenses − EMIs = surplus, compared with the proposed EMI. | C54: =Scorecard!C35 -> 3 | D54: =Scorecard!F35 -> 0 | E54: =IF(Scorecard!E35="Yes","✔ Said",IF(Scorecard!E35="Half","½ Half",IF(Scorecard!E35="No","✘ MISSED","?"))) -> ? | F54: =IF(Scorecard!G35="","",Scorecard!G35)
A55: E. FAMILY & HOME
A56: E1 | B56: =Scorecard!B37 -> HOME: own or rented, years living here, pucca / kachha, rooms; electricity bill in whose name; items seen — tractor, car, bike, TV, fridge, washing machine, smartphones (how many), cooler / AC, gas, electricity meter. Does the standard of living match the income claimed? | C56: =Scorecard!C37 -> 3 | D56: =Scorecard!F37 -> 0 | E56: =IF(Scorecard!E37="Yes","✔ Said",IF(Scorecard!E37="Half","½ Half",IF(Scorecard!E37="No","✘ MISSED","?"))) -> ? | F56: =IF(Scorecard!G37="","",Scorecard!G37)
A57: E2 ★ | B57: =Scorecard!B38 -> CO-BORROWER (wife / mother) met in person — knows the loan amount, the EMI and that the HOUSE WILL BE MORTGAGED. Each family member: what they do, aware of the loan, supportive? KYC originals (Aadhaar / PAN / Voter) and Samagra ID of borrower and ALL co-borrowers checked and matched. | C57: =Scorecard!C38 -> 4 | D57: =Scorecard!F38 -> 0 | E57: =IF(Scorecard!E38="Yes","✔ Said",IF(Scorecard!E38="Half","½ Half",IF(Scorecard!E38="No","✘ MISSED","?"))) -> ? | F57: =IF(Scorecard!G38="","",Scorecard!G38)
A58: E3 ★ | B58: =Scorecard!B39 -> 2 HOME NEIGHBOURS: name, mobile number, how long the family is staying here, conduct, any dispute. Photos taken. | C58: =Scorecard!C39 -> 3 | D58: =Scorecard!F39 -> 0 | E58: =IF(Scorecard!E39="Yes","✔ Said",IF(Scorecard!E39="Half","½ Half",IF(Scorecard!E39="No","✘ MISSED","?"))) -> ? | F58: =IF(Scorecard!G39="","",Scorecard!G39)
A59: E4 | B59: =Scorecard!B40 -> Told the customer and family: this is a Loan Against Property (house mortgaged), the EMI amount, Clean Track Reward (last 3 EMIs waived on clean repayment), ZERO COMMISSION — pay nobody, Prodigee works on trust and integrity. | C59: =Scorecard!C40 -> 2 | D59: =Scorecard!F40 -> 0 | E59: =IF(Scorecard!E40="Yes","✔ Said",IF(Scorecard!E40="Half","½ Half",IF(Scorecard!E40="No","✘ MISSED","?"))) -> ? | F59: =IF(Scorecard!G40="","",Scorecard!G40)
A60: F. PROPERTY
A61: F1 | B61: =Scorecard!B42 -> Property: house / shop / plot, self-occupied or rented out, pucca, age, area (sq.ft), road access, kitchen and toilet, condition. | C61: =Scorecard!C42 -> 3 | D61: =Scorecard!F42 -> 0 | E61: =IF(Scorecard!E42="Yes","✔ Said",IF(Scorecard!E42="Half","½ Half",IF(Scorecard!E42="No","✘ MISSED","?"))) -> ? | F61: =IF(Scorecard!G42="","",Scorecard!G42)
A62: F2 ★ | B62: =Scorecard!B43 -> ORIGINAL papers seen with your own eyes (Sale Deed / Patta / 5-pager — say which); in whose name; how he got it; mutation done? ALL owners and legal heirs are CO-BORROWERS on this loan — name them. | C62: =Scorecard!C43 -> 4 | D62: =Scorecard!F43 -> 0 | E62: =IF(Scorecard!E43="Yes","✔ Said",IF(Scorecard!E43="Half","½ Half",IF(Scorecard!E43="No","✘ MISSED","?"))) -> ? | F62: =IF(Scorecard!G43="","",Scorecard!G43)
A63: F3 | B63: =Scorecard!B44 -> Papers genuine? (registry seal and number, pages complete, Panchayat seal / signature). Already mortgaged with any other bank / finance company? Original papers lying with any other lender? Asked the family; checked CRIF for secured loans. For panchayat property: Patta / SVAMITVA record checked. | C63: =Scorecard!C44 -> 3 | D63: =Scorecard!F44 -> 0 | E63: =IF(Scorecard!E44="Yes","✔ Said",IF(Scorecard!E44="Half","½ Half",IF(Scorecard!E44="No","✘ MISSED","?"))) -> ? | F63: =IF(Scorecard!G44="","",Scorecard!G44)
A64: F4 | B64: =Scorecard!B45 -> Approximate value with the basis (local rate per sq.ft, a recent sale nearby, neighbour's view); distress value; loan amount vs value. | C64: =Scorecard!C45 -> 2 | D64: =Scorecard!F45 -> 0 | E64: =IF(Scorecard!E45="Yes","✔ Said",IF(Scorecard!E45="Half","½ Half",IF(Scorecard!E45="No","✘ MISSED","?"))) -> ? | F64: =IF(Scorecard!G45="","",Scorecard!G45)
A65: F5 | B65: =Scorecard!B46 -> Risks: any dispute, ST / tribal land, high-tension line / river bank / encroachment, negative area, demolition risk — say "none" if none. | C65: =Scorecard!C46 -> 2 | D65: =Scorecard!F46 -> 0 | E65: =IF(Scorecard!E46="Yes","✔ Said",IF(Scorecard!E46="Half","½ Half",IF(Scorecard!E46="No","✘ MISSED","?"))) -> ? | F65: =IF(Scorecard!G46="","",Scorecard!G46)
A66: G. LOAN PURPOSE & YOUR VIEW
A67: G1 | B67: =Scorecard!B48 -> Loan purpose: how much for what, where, when; is the need visible on the ground (empty shelves, loans to be closed); not a restricted use. | C67: =Scorecard!C48 -> 3 | D67: =Scorecard!F48 -> 0 | E67: =IF(Scorecard!E48="Yes","✔ Said",IF(Scorecard!E48="Half","½ Half",IF(Scorecard!E48="No","✘ MISSED","?"))) -> ? | F67: =IF(Scorecard!G48="","",Scorecard!G48)
A68: G2 ★ | B68: =Scorecard!B49 -> INTENT & INTEGRITY — answer each one clearly: (1) business genuine? (2) sales and purchase numbers true or inflated? (3) defaults justified? (4) regular defaulter? (5) family aware and supportive? (6) all property owners on the loan? (7) papers genuine? (8) customer open or evasive about accounts, bills, loans? (9) any middleman or commission? | C68: =Scorecard!C49 -> 4 | D68: =Scorecard!F49 -> 0 | E68: =IF(Scorecard!E49="Yes","✔ Said",IF(Scorecard!E49="Half","½ Half",IF(Scorecard!E49="No","✘ MISSED","?"))) -> ? | F68: =IF(Scorecard!G49="","",Scorecard!G49)
A69: G3 | B69: =Scorecard!B50 -> WARNING SIGNS seen — say each one, or say "none": staged / fake business · hidden loans · family unaware · doubtful papers or property mortgaged elsewhere · commission or middleman · numbers not matching AA / bills. | C69: =Scorecard!C50 -> 3 | D69: =Scorecard!F50 -> 0 | E69: =IF(Scorecard!E50="Yes","✔ Said",IF(Scorecard!E50="Half","½ Half",IF(Scorecard!E50="No","✘ MISSED","?"))) -> ? | F69: =IF(Scorecard!G50="","",Scorecard!G50)
A70: G4 | B70: =Scorecard!B51 -> What you could NOT verify — say it honestly. Your overall view: total family income vs loan asked, ability and intention to repay. (This is your view — the decision is taken later on PRAGATI.) | C70: =Scorecard!C51 -> 2 | D70: =Scorecard!F51 -> 0 | E70: =IF(Scorecard!E51="Yes","✔ Said",IF(Scorecard!E51="Half","½ Half",IF(Scorecard!E51="No","✘ MISSED","?"))) -> ? | F70: =IF(Scorecard!G51="","",Scorecard!G51)
A72: ★ = MUST item. A MUST item marked ½ or ✘ means the recording is not accepted — record those points again (a short extra recording covering only the missed points is fine).
